[{"round":"146380","betAmount":"0.001","bet":"bull","openPrice":"294.40041537","closePrice":"293.59","bullAmount":"20.427321288570205231","bearAmount":"12.832891218934349241","bullPayout":"1.628","bearPayout":"2.592","winner":"bear"},{"round":"146381","betAmount":"0.001","bet":"bull"},{"round":"146385","betAmount":"0.001","bet":"bull","openPrice":"294.4914","closePrice":"295.45261516","bullAmount":"4.760318132623451941","bearAmount":"7.865557600136211305","bullPayout":"2.652","bearPayout":"1.605","winner":"bull"},{"round":"146386","betAmount":"0.001","bet":"bull","openPrice":"295.45261516","closePrice":"295.72","bullAmount":"8.753281043435543137","bearAmount":"8.622869645708230843","bullPayout":"1.985","bearPayout":"2.015","winner":"bull"},{"round":"146387","betAmount":"0.001","bet":"bull","openPrice":"295.72","closePrice":"296.1009","bullAmount":"6.747768798458692364","bearAmount":"7.088075303172329248","bullPayout":"2.05","bearPayout":"1.952","winner":"bull"},{"round":"146388","betAmount":"0.001","bet":"bull","openPrice":"296.1009","closePrice":"295.7045","bullAmount":"6.190531840328034885","bearAmount":"12.01711998158857343","bullPayout":"2.941","bearPayout":"1.515","winner":"bear"},{"round":"146389","betAmount":"0.001","bet":"bull"},{"round":"146401","betAmount":"0.001","bet":"bear","openPrice":"293.56","closePrice":"292.5046","bullAmount":"8.932322998149229697","bearAmount":"7.123220381739812512","bullPayout":"1.797","bearPayout":"2.254","winner":"bear"},{"round":"146402","betAmount":"0.001","bet":"bear"},{"round":"146408","betAmount":"0.001","bet":"bull","openPrice":"299.00621","closePrice":"299.34401608","bullAmount":"10.24178919360519405","bearAmount":"9.73891133287935606","bullPayout":"1.951","bearPayout":"2.052","winner":"bull"},{"round":"146409","betAmount":"0.001","bet":"bull"},{"round":"146411","betAmount":"0.001","bet":"bull"},{"round":"146413","betAmount":"0.001","bet":"bear","openPrice":"300.78433749","closePrice":"298.63747","bullAmount":"10.977092106574654505","bearAmount":"12.440398504331716301","bullPayout":"2.133","bearPayout":"1.882","winner":"bear"},{"round":"146414","betAmount":"0.001","bet":"bear"}]